bluetooth_auto_recovery/__init__.py
bluetooth_auto_recovery/py.typed
bluetooth_auto_recovery/recover.py
bluetooth_auto_recovery/util.py
bluetooth_auto_recovery-1.5.2.dist-info/LICENSE
bluetooth_auto_recovery-1.5.2.dist-info/METADATA
bluetooth_auto_recovery-1.5.2.dist-info/WHEEL
bluetooth_auto_recovery-1.5.2.dist-info/RECORD
